console_ctrl/__init__.py
console_ctrl/__main__.py
console_ctrl-0.1.0.dist-info/LICENSE
console_ctrl-0.1.0.dist-info/METADATA
console_ctrl-0.1.0.dist-info/WHEEL
console_ctrl-0.1.0.dist-info/top_level.txt
console_ctrl-0.1.0.dist-info/RECORD
