Metadata-Version: 2.1
Name: console-ctrl
Version: 0.1.0
Summary: Send CTRL-C event to a target console process WITHOUT causing KeyboardInterrput at the caller side.
Home-page: https://github.com/arvinpan/console-ctrl
Author: Arvin Pan
Author-email: exarvin@gmail.com
License: UNKNOWN
Platform: UNKNOWN
Classifier: Programming Language :: Python :: 3
Classifier: License :: OSI Approved :: MIT License
Classifier: Operating System :: OS Independent
Requires-Python: >=3.6
